simmon.py
simmon-0.0.5.dist-info/LICENSE
simmon-0.0.5.dist-info/METADATA
simmon-0.0.5.dist-info/WHEEL
simmon-0.0.5.dist-info/top_level.txt
simmon-0.0.5.dist-info/RECORD
