Metadata-Version: 2.1
Name: simmon
Version: 0.0.5
Summary: A simple simulation monitor
Author: Roie Zemel
Keywords: simulation, data tracking
Classifier: Programming Language :: Python :: 3
Classifier: Operating System :: OS Independent
Requires-Python: >=3.8
License-File: LICENSE
Requires-Dist: matplotlib
